kpireport_mysql/__init__.py
kpireport_mysql/datasource.py
kpireport_mysql-0.0.2.dist-info/METADATA
kpireport_mysql-0.0.2.dist-info/WHEEL
kpireport_mysql-0.0.2.dist-info/entry_points.txt
kpireport_mysql-0.0.2.dist-info/top_level.txt
kpireport_mysql-0.0.2.dist-info/RECORD
